README.md
pyproject.toml
setup.cfg
setup.py
tests/test_tomldantic.py
tomldantic/__init__.py
tomldantic.egg-info/PKG-INFO
tomldantic.egg-info/SOURCES.txt
tomldantic.egg-info/dependency_links.txt
tomldantic.egg-info/requires.txt
tomldantic.egg-info/top_level.txt